superlevure/__init__.py
superlevure/__main__.py
superlevure-1.0.5.dist-info/LICENSE
superlevure-1.0.5.dist-info/METADATA
superlevure-1.0.5.dist-info/WHEEL
superlevure-1.0.5.dist-info/top_level.txt
superlevure-1.0.5.dist-info/RECORD
