Metadata-Version: 2.1
Name: superlevure
Version: 1.0.5
Summary: Superlevure library
Home-page: https://github.com/superlevure/superlevure
Author: superlevure
Author-email: superlevure.dev@gmail.com
License: UNKNOWN
Platform: UNKNOWN
Classifier: Programming Language :: Python :: 3
Classifier: License :: OSI Approved :: MIT License
Classifier: Operating System :: OS Independent
